html_librarian-0.0.1.dist-info/DESCRIPTION.rst
html_librarian-0.0.1.dist-info/METADATA
html_librarian-0.0.1.dist-info/RECORD
html_librarian-0.0.1.dist-info/WHEEL
html_librarian-0.0.1.dist-info/metadata.json
html_librarian-0.0.1.dist-info/top_level.txt
src/__init__.py
src/__version__.py
src/librarian.py
tests/__init__.py
tests/basictest.py
tests/context.py
