Metadata-Version: 2.0
Name: html-librarian
Version: 0.0.1
Summary: Never ever scrape the html off of a site multiple times ever again.
Home-page: https://github.com/alexsieusahai/Librarian
Author: Alex Sieusahai
Author-email: alexsieu14@gmail.com
License: Copyright 2018 Alex Sieusahai
